LICENSE
MANIFEST.in
README.md
setup.cfg
setup.py
tests/__init__.py
tests/test_readable.py
tests/test_improved/__init__.py
tests/test_improved/test_json.py
tests/test_simplified/__init__.py
tests/test_simplified/test_datetime.py
tests/test_simplified/test_env.py
tests/test_simplified/test_hashlib.py
thk_py/__init__.py
thk_py/readable.py
thk_py.egg-info/PKG-INFO
thk_py.egg-info/SOURCES.txt
thk_py.egg-info/dependency_links.txt
thk_py.egg-info/not-zip-safe
thk_py.egg-info/requires.txt
thk_py.egg-info/top_level.txt
thk_py/improved/__init__.py
thk_py/improved/json.py
thk_py/simplified/__init__.py
thk_py/simplified/datetime.py
thk_py/simplified/env.py
thk_py/simplified/hashlib.py